django_moo/__init__.py
django_moo/decorators.py
django_moo/delay.py
django_moo/settings.py
django_moo/utils.py
django_moo-1.3.1.dist-info/METADATA
django_moo-1.3.1.dist-info/WHEEL
django_moo-1.3.1.dist-info/license
django_moo-1.3.1.dist-info/top_level.txt
django_moo-1.3.1.dist-info/RECORD
