Metadata-Version: 2.1
Name: django-moo
Version: 1.3.1
Summary: come in handy
Home-page: https://gitee.com/nerd-mo/django_moo
Author: Xiaomo Lee
Author-email: 1904981400@qq.com
License: MIT
Platform: UNKNOWN
Classifier: License :: OSI Approved :: MIT License
Classifier: Programming Language :: Python
Classifier: Programming Language :: Python :: 3
Classifier: Programming Language :: Python :: 3.6
Classifier: Programming Language :: Python :: Implementation :: CPython
Classifier: Programming Language :: Python :: Implementation :: PyPy
Requires-Python: >=3.6.0
Requires-Dist: django
